Rom/rom.v
// memoria rom

module rom(
  input wire[11:0]L,
  output wire[7:0]D);

      reg[7:0] Memory[0:4095];

      initial begin
        $readmemb("memory.jmc", Memory);
      end

      assign data = Memory[L];
endmodule

Rom/rom_tb.v
module testbench();

reg[11:0]L;
wire[7:0]D;

rom mem(L, D);

initial begin
    #1
    $display("--------------");
    $display("Loc | L");
    $display("--------------");
    $monitor(" %b | %b ", L, D);
        L = 12'b000000000000;
    #1  L = 12'b000000000001;
    #1  L = 12'b000000000010;
    #1  L = 12'b000000000011;
    #1  L = 12'b000000000100;
    #1  L = 12'b000000000101;
    #1  L = 12'b000000000110;
    #1  L = 12'b000000000111;
    #1  L = 12'b000000001000;
    #1  L = 12'b000000001001;

end
    initial
    #200 $finish;

initial begin
  $dumpfile("rom_tb.vcd");
  $dumpvars(0, testbench);
end

endmodule

Rom/rom_tb.vcd
$date
	Sat Oct 24 19:28:05 2020
$end
$version
	Icarus Verilog
$end
$timescale
	1ps
$end
$scope module testbench $end
$var wire 8 ! D [7:0] $end
$var reg 12 " L [11:0] $end
$scope module mem $end
$var wire 8 # D [7:0] $end
$var wire 12 $ L [11:0] $end
$var wire 1 % data $end
$upscope $end
$upscope $end
$enddefinitions $end
#0
$dumpvars
x%
bx $
bz #
bx "
bz !
$end
#1
1%
b0 "
b0 $
#2
0%
b1 "
b1 $
#3
1%
b10 "
b10 $
#4
0%
b11 "
b11 $
#5
1%
b100 "
b100 $
#6
0%
b101 "
b101 $
#7
b110 "
b110 $
#8
1%
b111 "
b111 $
#9
b1000 "
b1000 $
#10
0%
b1001 "
b1001 $
