Alu/alu.v
// ALU

module alu(
  input wire[3:0]A,
  input wire[3:0]B,
  input wire[2:0]Com,
  output reg[3:0]Res);

      always @ (A or B or Com) begin

          case(Com)
              3'b000: Res = A & B;
              3'b001: Res = A | B;
              3'b010: Res = A + B;
              3'b100: Res = A & ~B;
              3'b101: Res = A | ~B;
              3'b110: Res = A - B;
              3'b111: Res = (A & B) ? 1:0;
              default: Res = 3'b000;
          endcase
      end
endmodule

Alu/alu_tb.v


module testbench();

reg[3:0]A;
reg[3:0]B;
reg[2:0]Com;
wire[3:0]Res;

alu test(A, B, Com, Res);

initial begin
    #1
    $display("---------------------------------");
    $display("| A | B | Com | Result |");
    $display("---------------------------------");
    $monitor(" %b | %b | %b | %b ", A, B, Com, Res);
        A = 4'b0000; B = 4'b0000; Com = 3'b000;
    #1 A = 4'b0001; B = 4'b0001; Com = 3'b000;
    #1 A = 4'b0001; B = 4'b0000; Com = 3'b000;
    #1 A = 4'b0100; B = 4'b0110; Com = 3'b000;
    #1 A = 4'b0001; B = 4'b0001; Com = 3'b001;
    #1 A = 4'b0001; B = 4'b0000; Com = 3'b001;
    #1 A = 4'b0000; B = 4'b0000; Com = 3'b001;
    #1 A = 4'b0001; B = 4'b0001; Com = 3'b010;
    #1 A = 4'b0010; B = 4'b0010; Com = 3'b010;
end

initial
    #21 $finish;

initial begin
    $dumpfile("alu_tb.vcd");
    $dumpvars(0, testbench);
end

endmodule

Alu/alu_tb.vcd
$date
	Sat Oct 24 19:32:20 2020
$end
$version
	Icarus Verilog
$end
$timescale
	1ps
$end
$scope module testbench $end
$var wire 4 ! Res [3:0] $end
$var reg 4 " A [3:0] $end
$var reg 4 # B [3:0] $end
$var reg 3 $ Com [2:0] $end
$scope module test $end
$var wire 4 % A [3:0] $end
$var wire 4 & B [3:0] $end
$var wire 3 ' Com [2:0] $end
$var reg 4 ( Res [3:0] $end
$upscope $end
$upscope $end
$enddefinitions $end
#0
$dumpvars
bx (
bx '
bx &
bx %
bx $
bx #
bx "
bx !
$end
#1
b0 !
b0 (
b0 $
b0 '
b0 #
b0 &
b0 "
b0 %
#2
b1 !
b1 (
b1 #
b1 &
b1 "
b1 %
#3
b0 !
b0 (
b0 #
b0 &
#4
b100 !
b100 (
b110 #
b110 &
b100 "
b100 %
#5
b1 !
b1 (
b1 $
b1 '
b1 #
b1 &
b1 "
b1 %
#6
b0 #
b0 &
#7
b0 !
b0 (
b0 "
b0 %
#8
b10 !
b10 (
b10 $
b10 '
b1 #
b1 &
b1 "
b1 %
#9
b100 !
b100 (
b10 #
b10 &
b10 "
b10 %
